sensors/__init__.py
sensors/time_interval_sensor.py
time_interval_sensor-0.1.5.dist-info/LICENSE
time_interval_sensor-0.1.5.dist-info/METADATA
time_interval_sensor-0.1.5.dist-info/WHEEL
time_interval_sensor-0.1.5.dist-info/top_level.txt
time_interval_sensor-0.1.5.dist-info/RECORD
