Metadata-Version: 2.1
Name: time_interval_sensor
Version: 0.1.5
Summary: A custom Airflow sensor to check if the current time is within a specific interval and time zone.
Author: Hrishikesh Tiwari
Author-email: htiwari1@gmail.com
License: MIT
Classifier: Programming Language :: Python :: 3
Classifier: License :: OSI Approved :: MIT License
Classifier: Operating System :: OS Independent
Requires-Python: >=3.6
License-File: LICENSE
Requires-Dist: apache-airflow (>=2.0.0)
Requires-Dist: pytz
